lerobot/__init__.py
lerobot/__version__.py
lerobot/calibrate.py
lerobot/find_cameras.py
lerobot/find_port.py
lerobot/record.py
lerobot/replay.py
lerobot/setup_motors.py
lerobot/teleoperate.py
lerobot/common/constants.py
lerobot/common/errors.py
lerobot/common/cameras/__init__.py
lerobot/common/cameras/camera.py
lerobot/common/cameras/configs.py
lerobot/common/cameras/utils.py
lerobot/common/cameras/opencv/__init__.py
lerobot/common/cameras/opencv/camera_opencv.py
lerobot/common/cameras/opencv/configuration_opencv.py
lerobot/common/cameras/realsense/__init__.py
lerobot/common/cameras/realsense/camera_realsense.py
lerobot/common/cameras/realsense/configuration_realsense.py
lerobot/common/datasets/backward_compatibility.py
lerobot/common/datasets/card_template.md
lerobot/common/datasets/compute_stats.py
lerobot/common/datasets/factory.py
lerobot/common/datasets/image_writer.py
lerobot/common/datasets/lerobot_dataset.py
lerobot/common/datasets/online_buffer.py
lerobot/common/datasets/sampler.py
lerobot/common/datasets/transforms.py
lerobot/common/datasets/utils.py
lerobot/common/datasets/video_utils.py
lerobot/common/datasets/push_dataset_to_hub/utils.py
lerobot/common/datasets/v2/batch_convert_dataset_v1_to_v2.py
lerobot/common/datasets/v2/convert_dataset_v1_to_v2.py
lerobot/common/datasets/v21/_remove_language_instruction.py
lerobot/common/datasets/v21/batch_convert_dataset_v20_to_v21.py
lerobot/common/datasets/v21/convert_dataset_v20_to_v21.py
lerobot/common/datasets/v21/convert_stats.py
lerobot/common/envs/__init__.py
lerobot/common/envs/configs.py
lerobot/common/envs/factory.py
lerobot/common/envs/utils.py
lerobot/common/model/kinematics.py
lerobot/common/motors/__init__.py
lerobot/common/motors/motors_bus.py
lerobot/common/motors/dynamixel/__init__.py
lerobot/common/motors/dynamixel/dynamixel.py
lerobot/common/motors/dynamixel/tables.py
lerobot/common/motors/feetech/__init__.py
lerobot/common/motors/feetech/feetech.py
lerobot/common/motors/feetech/tables.py
navrim_lerobot-0.1.0.post1.dist-info/licenses/LICENSE
navrim_lerobot-0.1.0.post1.dist-info/METADATA
navrim_lerobot-0.1.0.post1.dist-info/WHEEL
navrim_lerobot-0.1.0.post1.dist-info/top_level.txt
navrim_lerobot-0.1.0.post1.dist-info/RECORD
