Metadata-Version: 2.4
Name: navrim-lerobot
Version: 0.1.0.post1
Summary: 🤗 LeRobot: State-of-the-art Machine Learning for Real-World Robotics in Pytorch (Navrim fork)
Author-email: Rémi Cadène <re.cadene@gmail.com>, Simon Alibert <alibert.sim@gmail.com>, Alexander Soare <alexander.soare159@gmail.com>, Quentin Gallouédec <quentin.gallouedec@ec-lyon.fr>, Adil Zouitine <adilzouitinegm@gmail.com>, Thomas Wolf <thomaswolfcontact@gmail.com>, Steven Palma <imstevenpmwork@ieee.org>
License-Expression: Apache-2.0
Project-URL: homepage, https://github.com/navrim/navrim-lerobot
Project-URL: issues, https://github.com/navrim/navrim-lerobot/issues
Project-URL: discord, https://discord.gg/s3KuuzsPFb
Keywords: robotics,deep learning,pytorch
Classifier: Development Status :: 3 - Alpha
Classifier: Intended Audience :: Developers
Classifier: Intended Audience :: Education
Classifier: Intended Audience :: Science/Research
Classifier: Topic :: Software Development :: Build Tools
Classifier: Topic :: Scientific/Engineering :: Artificial Intelligence
Classifier: Programming Language :: Python :: 3.10
Requires-Python: >=3.10
License-File: LICENSE
Requires-Dist: cmake>=3.29.0.1
Requires-Dist: datasets>=2.19.0
Requires-Dist: deepdiff>=7.0.1
Requires-Dist: diffusers>=0.27.2
Requires-Dist: draccus==0.10.0
Requires-Dist: einops>=0.8.0
Requires-Dist: flask>=3.0.3
Requires-Dist: gdown>=5.1.0
Requires-Dist: gymnasium==0.29.1
Requires-Dist: h5py>=3.10.0
Requires-Dist: huggingface-hub[cli,hf-transfer]>=0.27.1; python_version < "4.0"
Requires-Dist: imageio[ffmpeg]>=2.34.0
Requires-Dist: jsonlines>=4.0.0
Requires-Dist: numba>=0.59.0
Requires-Dist: omegaconf>=2.3.0
Requires-Dist: opencv-python-headless>=4.9.0
Requires-Dist: packaging>=24.2
Requires-Dist: av>=14.2.0
Requires-Dist: pymunk<7.0.0,>=6.6.0
Requires-Dist: pynput>=1.7.7
Requires-Dist: pyserial>=3.5
Requires-Dist: pyzmq>=26.2.1
Requires-Dist: rerun-sdk>=0.21.0
Requires-Dist: scipy>=1.14.0
Requires-Dist: termcolor>=2.4.0
Requires-Dist: torch>=2.2.1
Requires-Dist: torchcodec>=0.2.1; sys_platform != "win32" and (sys_platform != "linux" or (platform_machine != "aarch64" and platform_machine != "arm64" and platform_machine != "armv7l")) and (sys_platform != "darwin" or platform_machine != "x86_64")
Requires-Dist: torchvision>=0.21.0
Requires-Dist: wandb>=0.16.3
Requires-Dist: zarr>=2.17.0
Provides-Extra: aloha
Requires-Dist: gym-aloha>=0.1.1; python_version < "4.0" and extra == "aloha"
Provides-Extra: docs
Requires-Dist: hf-doc-builder>=0.5.0; extra == "docs"
Requires-Dist: watchdog>=6.0.0; extra == "docs"
Provides-Extra: dev
Requires-Dist: pre-commit>=3.7.0; extra == "dev"
Requires-Dist: debugpy>=1.8.1; extra == "dev"
Provides-Extra: dynamixel
Requires-Dist: dynamixel-sdk>=3.7.31; extra == "dynamixel"
Provides-Extra: feetech
Requires-Dist: feetech-servo-sdk>=1.0.0; extra == "feetech"
Provides-Extra: gamepad
Requires-Dist: pygame>=2.5.1; extra == "gamepad"
Requires-Dist: hidapi>=0.14.0; extra == "gamepad"
Provides-Extra: intelrealsense
Requires-Dist: pyrealsense2>=2.55.1.6486; sys_platform != "darwin" and extra == "intelrealsense"
Requires-Dist: pyrealsense2-macosx>=2.54; sys_platform == "darwin" and extra == "intelrealsense"
Provides-Extra: pi0
Requires-Dist: transformers>=4.50.3; extra == "pi0"
Provides-Extra: smolvla
Requires-Dist: transformers>=4.50.3; extra == "smolvla"
Requires-Dist: num2words>=0.5.14; extra == "smolvla"
Requires-Dist: accelerate>=1.7.0; extra == "smolvla"
Requires-Dist: safetensors>=0.4.3; extra == "smolvla"
Provides-Extra: pusht
Requires-Dist: gym-pusht>=0.1.5; python_version < "4.0" and extra == "pusht"
Provides-Extra: stretch
Requires-Dist: hello-robot-stretch-body>=0.7.27; (python_version < "4.0" and sys_platform == "linux") and extra == "stretch"
Requires-Dist: pyrender>=0.1.45; sys_platform == "linux" and extra == "stretch"
Requires-Dist: pyrealsense2>=2.55.1.6486; sys_platform != "darwin" and extra == "stretch"
Provides-Extra: test
Requires-Dist: pytest>=8.1.0; extra == "test"
Requires-Dist: pytest-timeout>=2.4.0; extra == "test"
Requires-Dist: pytest-cov>=5.0.0; extra == "test"
Requires-Dist: pyserial>=3.5; extra == "test"
Requires-Dist: mock-serial>=0.0.1; sys_platform != "win32" and extra == "test"
Provides-Extra: hilserl
Requires-Dist: transformers>=4.50.3; extra == "hilserl"
Requires-Dist: gym-hil>=0.1.8; extra == "hilserl"
Requires-Dist: protobuf>=5.29.3; extra == "hilserl"
Requires-Dist: grpcio==1.71.0; extra == "hilserl"
Provides-Extra: umi
Requires-Dist: imagecodecs>=2024.1.1; extra == "umi"
Provides-Extra: video-benchmark
Requires-Dist: scikit-image>=0.23.2; extra == "video-benchmark"
Requires-Dist: pandas>=2.2.2; extra == "video-benchmark"
Provides-Extra: xarm
Requires-Dist: gym-xarm>=0.1.1; python_version < "4.0" and extra == "xarm"
Dynamic: license-file
